YunxinServerApiSigner/__init__.py
YunxinServerApiSigner/main.py
YunxinServerApiSigner-1.0.2.dist-info/METADATA
YunxinServerApiSigner-1.0.2.dist-info/WHEEL
YunxinServerApiSigner-1.0.2.dist-info/entry_points.txt
YunxinServerApiSigner-1.0.2.dist-info/top_level.txt
YunxinServerApiSigner-1.0.2.dist-info/RECORD
